hldb.py
hldb-0.5.2.dist-info/METADATA
hldb-0.5.2.dist-info/WHEEL
hldb-0.5.2.dist-info/top_level.txt
hldb-0.5.2.dist-info/RECORD
